<?xml version="1.0"?>
<iepd:FoiaAnnualReport xmlns:iepd="http://leisp.usdoj.gov/niem/FoiaAnnualReport/exchange/1.03" xsi:schemaLocation="http://leisp.usdoj.gov/niem/FoiaAnnualReport/exchange/1.03 ../schema/exchange/FoiaAnnualReport.xsd" xmlns:foia="http://leisp.usdoj.gov/niem/FoiaAnnualReport/extension/1.03" xmlns:i="http://niem.gov/niem/appinfo/2.0" xmlns:j="http://niem.gov/niem/domains/jxdm/4.1" xmlns:nc="http://niem.gov/niem/niem-core/2.0" xmlns:s="http://niem.gov/niem/structures/2.0" xmlns:xsi="http://www.w3.org/2001/XMLSchema-instance"><nc:DocumentApplicationName nc:applicationVersionText="1.1">FOIA Annual Report Workbook</nc:DocumentApplicationName><nc:DocumentCreationDate><nc:Date>2012-01-13</nc:Date></nc:DocumentCreationDate><nc:DocumentDescriptionText>FOIA Annual Report</nc:DocumentDescriptionText><nc:Organization s:id="ORG0"><nc:OrganizationAbbreviationText>NRPC</nc:OrganizationAbbreviationText><nc:OrganizationName>National Railroad Passenger Corporation</nc:OrganizationName></nc:Organization><foia:DocumentFiscalYearDate>2011</foia:DocumentFiscalYearDate><foia:Exemption3StatuteSection><foia:ReliedUponStatute s:id="ES8"><j:StatuteDescriptionText>41 U.S.C. Section 253b(m)(1)</j:StatuteDescriptionText><foia:ReliedUponStatuteInformationWithheldText>Bid proposals not incorporated in contracts</foia:ReliedUponStatuteInformationWithheldText><nc:Case><nc:CaseTitleText>None</nc:CaseTitleText></nc:Case></foia:ReliedUponStatute><foia:ReliedUponStatuteOrganizationAssociation><foia:ComponentDataReference s:ref="ES8"/><nc:OrganizationReference s:ref="ORG0"/><foia:ReliedUponStatuteQuantity>3</foia:ReliedUponStatuteQuantity></foia:ReliedUponStatuteOrganizationAssociation></foia:Exemption3StatuteSection><foia:ProcessedRequestSection><foia:ProcessingStatistics s:id="PS1"><foia:ProcessingStatisticsPendingAtStartQuantity>54</foia:ProcessingStatisticsPendingAtStartQuantity><foia:ProcessingStatisticsReceivedQuantity>172</foia:ProcessingStatisticsReceivedQuantity><foia:ProcessingStatisticsProcessedQuantity>171</foia:ProcessingStatisticsProcessedQuantity><foia:ProcessingStatisticsPendingAtEndQuantity>55</foia:ProcessingStatisticsPendingAtEndQuantity></foia:ProcessingStatistics><foia:ProcessingStatisticsOrganizationAssociation><foia:ComponentDataReference s:ref="PS1"/><nc:OrganizationReference s:ref="ORG0"/></foia:ProcessingStatisticsOrganizationAssociation><foia:FootnoteText>An adjustment had to be made with the number of pending requests at the start of the fiscal year.  Some pending requests had not been entered into the FOIA tracking system.</foia:FootnoteText></foia:ProcessedRequestSection><foia:RequestDispositionSection><foia:RequestDisposition s:id="RD1"><foia:RequestDispositionFullGrantQuantity>59</foia:RequestDispositionFullGrantQuantity><foia:RequestDispositionPartialGrantQuantity>34</foia:RequestDispositionPartialGrantQuantity><foia:RequestDispositionFullExemptionDenialQuantity>9</foia:RequestDispositionFullExemptionDenialQuantity><foia:NonExemptionDenial><foia:NonExemptionDenialReasonCode>NoRecords</foia:NonExemptionDenialReasonCode><foia:NonExemptionDenialQuantity>10</foia:NonExemptionDenialQuantity></foia:NonExemptionDenial><foia:NonExemptionDenial><foia:NonExemptionDenialReasonCode>Withdrawn</foia:NonExemptionDenialReasonCode><foia:NonExemptionDenialQuantity>29</foia:NonExemptionDenialQuantity></foia:NonExemptionDenial><foia:NonExemptionDenial><foia:NonExemptionDenialReasonCode>FeeRelated</foia:NonExemptionDenialReasonCode><foia:NonExemptionDenialQuantity>20</foia:NonExemptionDenialQuantity></foia:NonExemptionDenial><foia:NonExemptionDenial><foia:NonExemptionDenialReasonCode>ImproperRequest</foia:NonExemptionDenialReasonCode><foia:NonExemptionDenialQuantity>2</foia:NonExemptionDenialQuantity></foia:NonExemptionDenial><foia:NonExemptionDenial><foia:NonExemptionDenialReasonCode>NotAgency</foia:NonExemptionDenialReasonCode><foia:NonExemptionDenialQuantity>4</foia:NonExemptionDenialQuantity></foia:NonExemptionDenial><foia:NonExemptionDenial><foia:NonExemptionDenialReasonCode>Duplicate</foia:NonExemptionDenialReasonCode><foia:NonExemptionDenialQuantity>4</foia:NonExemptionDenialQuantity></foia:NonExemptionDenial><foia:RequestDispositionTotalQuantity>171</foia:RequestDispositionTotalQuantity></foia:RequestDisposition><foia:RequestDispositionOrganizationAssociation><foia:ComponentDataReference s:ref="RD1"/><nc:OrganizationReference s:ref="ORG0"/></foia:RequestDispositionOrganizationAssociation></foia:RequestDispositionSection><foia:RequestDenialOtherReasonSection><foia:ComponentOtherDenialReason s:id="CODR8"><foia:OtherDenialReason><foia:OtherDenialReasonDescriptionText>N/A</foia:OtherDenialReasonDescriptionText><foia:OtherDenialReasonQuantity>0</foia:OtherDenialReasonQuantity></foia:OtherDenialReason><foia:ComponentOtherDenialReasonQuantity>0</foia:ComponentOtherDenialReasonQuantity></foia:ComponentOtherDenialReason><foia:OtherDenialReasonOrganizationAssociation><foia:ComponentDataReference s:ref="CODR8"/><nc:OrganizationReference s:ref="ORG0"/></foia:OtherDenialReasonOrganizationAssociation></foia:RequestDenialOtherReasonSection><foia:RequestDispositionAppliedExemptionsSection><foia:ComponentAppliedExemptions s:id="RDE1"><foia:AppliedExemption><foia:AppliedExemptionCode>Ex. 2</foia:AppliedExemptionCode><foia:AppliedExemptionQuantity>1</foia:AppliedExemptionQuantity></foia:AppliedExemption><foia:AppliedExemption><foia:AppliedExemptionCode>Ex. 3</foia:AppliedExemptionCode><foia:AppliedExemptionQuantity>3</foia:AppliedExemptionQuantity></foia:AppliedExemption><foia:AppliedExemption><foia:AppliedExemptionCode>Ex. 4</foia:AppliedExemptionCode><foia:AppliedExemptionQuantity>5</foia:AppliedExemptionQuantity></foia:AppliedExemption><foia:AppliedExemption><foia:AppliedExemptionCode>Ex. 5</foia:AppliedExemptionCode><foia:AppliedExemptionQuantity>7</foia:AppliedExemptionQuantity></foia:AppliedExemption><foia:AppliedExemption><foia:AppliedExemptionCode>Ex. 6</foia:AppliedExemptionCode><foia:AppliedExemptionQuantity>25</foia:AppliedExemptionQuantity></foia:AppliedExemption><foia:AppliedExemption><foia:AppliedExemptionCode>Ex. 7(A)</foia:AppliedExemptionCode><foia:AppliedExemptionQuantity>6</foia:AppliedExemptionQuantity></foia:AppliedExemption><foia:AppliedExemption><foia:AppliedExemptionCode>Ex. 7(C)</foia:AppliedExemptionCode><foia:AppliedExemptionQuantity>16</foia:AppliedExemptionQuantity></foia:AppliedExemption><foia:AppliedExemption><foia:AppliedExemptionCode>Ex. 7(D)</foia:AppliedExemptionCode><foia:AppliedExemptionQuantity>1</foia:AppliedExemptionQuantity></foia:AppliedExemption></foia:ComponentAppliedExemptions><foia:ComponentAppliedExemptionsOrganizationAssociation><foia:ComponentDataReference s:ref="RDE1"/><nc:OrganizationReference s:ref="ORG0"/></foia:ComponentAppliedExemptionsOrganizationAssociation></foia:RequestDispositionAppliedExemptionsSection><foia:ProcessedAppealSection><foia:ProcessingStatistics s:id="PA1"><foia:ProcessingStatisticsPendingAtStartQuantity>2</foia:ProcessingStatisticsPendingAtStartQuantity><foia:ProcessingStatisticsReceivedQuantity>7</foia:ProcessingStatisticsReceivedQuantity><foia:ProcessingStatisticsProcessedQuantity>7</foia:ProcessingStatisticsProcessedQuantity><foia:ProcessingStatisticsPendingAtEndQuantity>2</foia:ProcessingStatisticsPendingAtEndQuantity></foia:ProcessingStatistics><foia:ProcessingStatisticsOrganizationAssociation><foia:ComponentDataReference s:ref="PA1"/><nc:OrganizationReference s:ref="ORG0"/></foia:ProcessingStatisticsOrganizationAssociation></foia:ProcessedAppealSection><foia:AppealDispositionSection><foia:AppealDisposition s:id="AD1"><foia:AppealDispositionAffirmedQuantity>3</foia:AppealDispositionAffirmedQuantity><foia:AppealDispositionPartialQuantity>0</foia:AppealDispositionPartialQuantity><foia:AppealDispositionReversedQuantity>0</foia:AppealDispositionReversedQuantity><foia:AppealDispositionOtherQuantity>4</foia:AppealDispositionOtherQuantity><foia:AppealDispositionTotalQuantity>7</foia:AppealDispositionTotalQuantity></foia:AppealDisposition><foia:AppealDispositionOrganizationAssociation><foia:ComponentDataReference s:ref="AD1"/><nc:OrganizationReference s:ref="ORG0"/></foia:AppealDispositionOrganizationAssociation></foia:AppealDispositionSection><foia:AppealDispositionAppliedExemptionsSection><foia:ComponentAppliedExemptions s:id="ADE1"><foia:AppliedExemption><foia:AppliedExemptionCode>Ex. 3</foia:AppliedExemptionCode><foia:AppliedExemptionQuantity>1</foia:AppliedExemptionQuantity></foia:AppliedExemption><foia:AppliedExemption><foia:AppliedExemptionCode>Ex. 4</foia:AppliedExemptionCode><foia:AppliedExemptionQuantity>1</foia:AppliedExemptionQuantity></foia:AppliedExemption><foia:AppliedExemption><foia:AppliedExemptionCode>Ex. 5</foia:AppliedExemptionCode><foia:AppliedExemptionQuantity>2</foia:AppliedExemptionQuantity></foia:AppliedExemption><foia:AppliedExemption><foia:AppliedExemptionCode>Ex. 6</foia:AppliedExemptionCode><foia:AppliedExemptionQuantity>4</foia:AppliedExemptionQuantity></foia:AppliedExemption><foia:AppliedExemption><foia:AppliedExemptionCode>Ex. 7(A)</foia:AppliedExemptionCode><foia:AppliedExemptionQuantity>1</foia:AppliedExemptionQuantity></foia:AppliedExemption><foia:AppliedExemption><foia:AppliedExemptionCode>Ex. 7(C)</foia:AppliedExemptionCode><foia:AppliedExemptionQuantity>2</foia:AppliedExemptionQuantity></foia:AppliedExemption></foia:ComponentAppliedExemptions><foia:ComponentAppliedExemptionsOrganizationAssociation><foia:ComponentDataReference s:ref="ADE1"/><nc:OrganizationReference s:ref="ORG0"/></foia:ComponentAppliedExemptionsOrganizationAssociation></foia:AppealDispositionAppliedExemptionsSection><foia:AppealNonExemptionDenialSection><foia:AppealNonExemptionDenial s:id="ANE1"><foia:NonExemptionDenial><foia:NonExemptionDenialReasonCode>Withdrawn</foia:NonExemptionDenialReasonCode><foia:NonExemptionDenialQuantity>2</foia:NonExemptionDenialQuantity></foia:NonExemptionDenial><foia:NonExemptionDenial><foia:NonExemptionDenialReasonCode>Other</foia:NonExemptionDenialReasonCode><foia:NonExemptionDenialQuantity>2</foia:NonExemptionDenialQuantity></foia:NonExemptionDenial></foia:AppealNonExemptionDenial><foia:AppealNonExemptionDenialOrganizationAssociation><foia:ComponentDataReference s:ref="ANE1"/><nc:OrganizationReference s:ref="ORG0"/></foia:AppealNonExemptionDenialOrganizationAssociation></foia:AppealNonExemptionDenialSection><foia:AppealDenialOtherReasonSection><foia:ComponentOtherDenialReason s:id="ADOR8"><foia:OtherDenialReason><foia:OtherDenialReasonDescriptionText>Not a proper appeal</foia:OtherDenialReasonDescriptionText><foia:OtherDenialReasonQuantity>2</foia:OtherDenialReasonQuantity></foia:OtherDenialReason><foia:ComponentOtherDenialReasonQuantity>2</foia:ComponentOtherDenialReasonQuantity></foia:ComponentOtherDenialReason><foia:OtherDenialReasonOrganizationAssociation><foia:ComponentDataReference s:ref="ADOR8"/><nc:OrganizationReference s:ref="ORG0"/></foia:OtherDenialReasonOrganizationAssociation></foia:AppealDenialOtherReasonSection><foia:AppealResponseTimeSection><foia:ResponseTime s:id="ART0"><foia:ResponseTimeMedianDaysValue>36</foia:ResponseTimeMedianDaysValue><foia:ResponseTimeAverageDaysValue>100</foia:ResponseTimeAverageDaysValue><foia:ResponseTimeLowestDaysValue>7</foia:ResponseTimeLowestDaysValue><foia:ResponseTimeHighestDaysValue>488</foia:ResponseTimeHighestDaysValue></foia:ResponseTime><foia:ResponseTimeOrganizationAssociation><foia:ComponentDataReference s:ref="ART0"/><nc:OrganizationReference s:ref="ORG0"/></foia:ResponseTimeOrganizationAssociation></foia:AppealResponseTimeSection><foia:OldestPendingAppealSection><foia:OldestPendingItems s:id="OPA10"><foia:OldItem><foia:OldItemReceiptDate>2009-12-14</foia:OldItemReceiptDate><foia:OldItemPendingDaysQuantity>452</foia:OldItemPendingDaysQuantity></foia:OldItem><foia:OldItem><foia:OldItemReceiptDate>2011-09-30</foia:OldItemReceiptDate><foia:OldItemPendingDaysQuantity>1</foia:OldItemPendingDaysQuantity></foia:OldItem></foia:OldestPendingItems><foia:OldestPendingItemsOrganizationAssociation><foia:ComponentDataReference s:ref="OPA10"/><nc:OrganizationReference s:ref="ORG0"/></foia:OldestPendingItemsOrganizationAssociation><foia:FootnoteText>0</foia:FootnoteText></foia:OldestPendingAppealSection><foia:ProcessedResponseTimeSection><foia:ProcessedResponseTime s:id="PRT0"><foia:SimpleResponseTime><foia:ResponseTimeMedianDaysValue>6</foia:ResponseTimeMedianDaysValue><foia:ResponseTimeAverageDaysValue>30</foia:ResponseTimeAverageDaysValue><foia:ResponseTimeLowestDaysValue>1</foia:ResponseTimeLowestDaysValue><foia:ResponseTimeHighestDaysValue>270</foia:ResponseTimeHighestDaysValue></foia:SimpleResponseTime><foia:ComplexResponseTime><foia:ResponseTimeMedianDaysValue>28</foia:ResponseTimeMedianDaysValue><foia:ResponseTimeAverageDaysValue>90</foia:ResponseTimeAverageDaysValue><foia:ResponseTimeLowestDaysValue>1</foia:ResponseTimeLowestDaysValue><foia:ResponseTimeHighestDaysValue>725</foia:ResponseTimeHighestDaysValue></foia:ComplexResponseTime><foia:ExpeditedResponseTime><foia:ResponseTimeMedianDaysValue>127</foia:ResponseTimeMedianDaysValue><foia:ResponseTimeAverageDaysValue>127</foia:ResponseTimeAverageDaysValue><foia:ResponseTimeLowestDaysValue>37</foia:ResponseTimeLowestDaysValue><foia:ResponseTimeHighestDaysValue>217</foia:ResponseTimeHighestDaysValue></foia:ExpeditedResponseTime></foia:ProcessedResponseTime><foia:ProcessedResponseTimeOrganizationAssociation><foia:ComponentDataReference s:ref="PRT0"/><nc:OrganizationReference s:ref="ORG0"/></foia:ProcessedResponseTimeOrganizationAssociation></foia:ProcessedResponseTimeSection><foia:InformationGrantedResponseTimeSection><foia:ProcessedResponseTime s:id="IGR0"><foia:SimpleResponseTime><foia:ResponseTimeMedianDaysValue>6</foia:ResponseTimeMedianDaysValue><foia:ResponseTimeAverageDaysValue>32</foia:ResponseTimeAverageDaysValue><foia:ResponseTimeLowestDaysValue>1</foia:ResponseTimeLowestDaysValue><foia:ResponseTimeHighestDaysValue>270</foia:ResponseTimeHighestDaysValue></foia:SimpleResponseTime><foia:ComplexResponseTime><foia:ResponseTimeMedianDaysValue>27</foia:ResponseTimeMedianDaysValue><foia:ResponseTimeAverageDaysValue>75</foia:ResponseTimeAverageDaysValue><foia:ResponseTimeLowestDaysValue>1</foia:ResponseTimeLowestDaysValue><foia:ResponseTimeHighestDaysValue>688</foia:ResponseTimeHighestDaysValue></foia:ComplexResponseTime><foia:ExpeditedResponseTime><foia:ResponseTimeMedianDaysValue>217</foia:ResponseTimeMedianDaysValue><foia:ResponseTimeAverageDaysValue>217</foia:ResponseTimeAverageDaysValue><foia:ResponseTimeLowestDaysValue>217</foia:ResponseTimeLowestDaysValue><foia:ResponseTimeHighestDaysValue>217</foia:ResponseTimeHighestDaysValue></foia:ExpeditedResponseTime></foia:ProcessedResponseTime><foia:ProcessedResponseTimeOrganizationAssociation><foia:ComponentDataReference s:ref="IGR0"/><nc:OrganizationReference s:ref="ORG0"/></foia:ProcessedResponseTimeOrganizationAssociation></foia:InformationGrantedResponseTimeSection><foia:SimpleResponseTimeIncrementsSection><foia:ComponentResponseTimeIncrements s:id="SRT1"><foia:TimeIncrement><foia:TimeIncrementCode>1-20</foia:TimeIncrementCode><foia:TimeIncrementProcessedQuantity>34</foia:TimeIncrementProcessedQuantity></foia:TimeIncrement><foia:TimeIncrement><foia:TimeIncrementCode>21-40</foia:TimeIncrementCode><foia:TimeIncrementProcessedQuantity>3</foia:TimeIncrementProcessedQuantity></foia:TimeIncrement><foia:TimeIncrement><foia:TimeIncrementCode>41-60</foia:TimeIncrementCode><foia:TimeIncrementProcessedQuantity>2</foia:TimeIncrementProcessedQuantity></foia:TimeIncrement><foia:TimeIncrement><foia:TimeIncrementCode>61-80</foia:TimeIncrementCode><foia:TimeIncrementProcessedQuantity>1</foia:TimeIncrementProcessedQuantity></foia:TimeIncrement><foia:TimeIncrement><foia:TimeIncrementCode>81-100</foia:TimeIncrementCode><foia:TimeIncrementProcessedQuantity>0</foia:TimeIncrementProcessedQuantity></foia:TimeIncrement><foia:TimeIncrement><foia:TimeIncrementCode>101-120</foia:TimeIncrementCode><foia:TimeIncrementProcessedQuantity>0</foia:TimeIncrementProcessedQuantity></foia:TimeIncrement><foia:TimeIncrement><foia:TimeIncrementCode>121-140</foia:TimeIncrementCode><foia:TimeIncrementProcessedQuantity>1</foia:TimeIncrementProcessedQuantity></foia:TimeIncrement><foia:TimeIncrement><foia:TimeIncrementCode>141-160</foia:TimeIncrementCode><foia:TimeIncrementProcessedQuantity>0</foia:TimeIncrementProcessedQuantity></foia:TimeIncrement><foia:TimeIncrement><foia:TimeIncrementCode>161-180</foia:TimeIncrementCode><foia:TimeIncrementProcessedQuantity>0</foia:TimeIncrementProcessedQuantity></foia:TimeIncrement><foia:TimeIncrement><foia:TimeIncrementCode>181-200</foia:TimeIncrementCode><foia:TimeIncrementProcessedQuantity>0</foia:TimeIncrementProcessedQuantity></foia:TimeIncrement><foia:TimeIncrement><foia:TimeIncrementCode>201-300</foia:TimeIncrementCode><foia:TimeIncrementProcessedQuantity>3</foia:TimeIncrementProcessedQuantity></foia:TimeIncrement><foia:TimeIncrement><foia:TimeIncrementCode>301-400</foia:TimeIncrementCode><foia:TimeIncrementProcessedQuantity>0</foia:TimeIncrementProcessedQuantity></foia:TimeIncrement><foia:TimeIncrement><foia:TimeIncrementCode>401+</foia:TimeIncrementCode><foia:TimeIncrementProcessedQuantity>0</foia:TimeIncrementProcessedQuantity></foia:TimeIncrement><foia:TimeIncrementTotalQuantity>44</foia:TimeIncrementTotalQuantity></foia:ComponentResponseTimeIncrements><foia:ResponseTimeIncrementsOrganizationAssociation><foia:ComponentDataReference s:ref="SRT1"/><nc:OrganizationReference s:ref="ORG0"/></foia:ResponseTimeIncrementsOrganizationAssociation></foia:SimpleResponseTimeIncrementsSection><foia:ComplexResponseTimeIncrementsSection><foia:ComponentResponseTimeIncrements s:id="CRT1"><foia:TimeIncrement><foia:TimeIncrementCode>1-20</foia:TimeIncrementCode><foia:TimeIncrementProcessedQuantity>55</foia:TimeIncrementProcessedQuantity></foia:TimeIncrement><foia:TimeIncrement><foia:TimeIncrementCode>21-40</foia:TimeIncrementCode><foia:TimeIncrementProcessedQuantity>17</foia:TimeIncrementProcessedQuantity></foia:TimeIncrement><foia:TimeIncrement><foia:TimeIncrementCode>41-60</foia:TimeIncrementCode><foia:TimeIncrementProcessedQuantity>11</foia:TimeIncrementProcessedQuantity></foia:TimeIncrement><foia:TimeIncrement><foia:TimeIncrementCode>61-80</foia:TimeIncrementCode><foia:TimeIncrementProcessedQuantity>9</foia:TimeIncrementProcessedQuantity></foia:TimeIncrement><foia:TimeIncrement><foia:TimeIncrementCode>81-100</foia:TimeIncrementCode><foia:TimeIncrementProcessedQuantity>0</foia:TimeIncrementProcessedQuantity></foia:TimeIncrement><foia:TimeIncrement><foia:TimeIncrementCode>101-120</foia:TimeIncrementCode><foia:TimeIncrementProcessedQuantity>4</foia:TimeIncrementProcessedQuantity></foia:TimeIncrement><foia:TimeIncrement><foia:TimeIncrementCode>121-140</foia:TimeIncrementCode><foia:TimeIncrementProcessedQuantity>3</foia:TimeIncrementProcessedQuantity></foia:TimeIncrement><foia:TimeIncrement><foia:TimeIncrementCode>141-160</foia:TimeIncrementCode><foia:TimeIncrementProcessedQuantity>3</foia:TimeIncrementProcessedQuantity></foia:TimeIncrement><foia:TimeIncrement><foia:TimeIncrementCode>161-180</foia:TimeIncrementCode><foia:TimeIncrementProcessedQuantity>3</foia:TimeIncrementProcessedQuantity></foia:TimeIncrement><foia:TimeIncrement><foia:TimeIncrementCode>181-200</foia:TimeIncrementCode><foia:TimeIncrementProcessedQuantity>2</foia:TimeIncrementProcessedQuantity></foia:TimeIncrement><foia:TimeIncrement><foia:TimeIncrementCode>201-300</foia:TimeIncrementCode><foia:TimeIncrementProcessedQuantity>7</foia:TimeIncrementProcessedQuantity></foia:TimeIncrement><foia:TimeIncrement><foia:TimeIncrementCode>301-400</foia:TimeIncrementCode><foia:TimeIncrementProcessedQuantity>5</foia:TimeIncrementProcessedQuantity></foia:TimeIncrement><foia:TimeIncrement><foia:TimeIncrementCode>401+</foia:TimeIncrementCode><foia:TimeIncrementProcessedQuantity>6</foia:TimeIncrementProcessedQuantity></foia:TimeIncrement><foia:TimeIncrementTotalQuantity>125</foia:TimeIncrementTotalQuantity></foia:ComponentResponseTimeIncrements><foia:ResponseTimeIncrementsOrganizationAssociation><foia:ComponentDataReference s:ref="CRT1"/><nc:OrganizationReference s:ref="ORG0"/></foia:ResponseTimeIncrementsOrganizationAssociation></foia:ComplexResponseTimeIncrementsSection><foia:ExpeditedResponseTimeIncrementsSection><foia:ComponentResponseTimeIncrements s:id="ERT1"><foia:TimeIncrement><foia:TimeIncrementCode>1-20</foia:TimeIncrementCode><foia:TimeIncrementProcessedQuantity>0</foia:TimeIncrementProcessedQuantity></foia:TimeIncrement><foia:TimeIncrement><foia:TimeIncrementCode>21-40</foia:TimeIncrementCode><foia:TimeIncrementProcessedQuantity>1</foia:TimeIncrementProcessedQuantity></foia:TimeIncrement><foia:TimeIncrement><foia:TimeIncrementCode>41-60</foia:TimeIncrementCode><foia:TimeIncrementProcessedQuantity>0</foia:TimeIncrementProcessedQuantity></foia:TimeIncrement><foia:TimeIncrement><foia:TimeIncrementCode>61-80</foia:TimeIncrementCode><foia:TimeIncrementProcessedQuantity>0</foia:TimeIncrementProcessedQuantity></foia:TimeIncrement><foia:TimeIncrement><foia:TimeIncrementCode>81-100</foia:TimeIncrementCode><foia:TimeIncrementProcessedQuantity>0</foia:TimeIncrementProcessedQuantity></foia:TimeIncrement><foia:TimeIncrement><foia:TimeIncrementCode>101-120</foia:TimeIncrementCode><foia:TimeIncrementProcessedQuantity>0</foia:TimeIncrementProcessedQuantity></foia:TimeIncrement><foia:TimeIncrement><foia:TimeIncrementCode>121-140</foia:TimeIncrementCode><foia:TimeIncrementProcessedQuantity>0</foia:TimeIncrementProcessedQuantity></foia:TimeIncrement><foia:TimeIncrement><foia:TimeIncrementCode>141-160</foia:TimeIncrementCode><foia:TimeIncrementProcessedQuantity>0</foia:TimeIncrementProcessedQuantity></foia:TimeIncrement><foia:TimeIncrement><foia:TimeIncrementCode>161-180</foia:TimeIncrementCode><foia:TimeIncrementProcessedQuantity>0</foia:TimeIncrementProcessedQuantity></foia:TimeIncrement><foia:TimeIncrement><foia:TimeIncrementCode>181-200</foia:TimeIncrementCode><foia:TimeIncrementProcessedQuantity>0</foia:TimeIncrementProcessedQuantity></foia:TimeIncrement><foia:TimeIncrement><foia:TimeIncrementCode>201-300</foia:TimeIncrementCode><foia:TimeIncrementProcessedQuantity>1</foia:TimeIncrementProcessedQuantity></foia:TimeIncrement><foia:TimeIncrement><foia:TimeIncrementCode>301-400</foia:TimeIncrementCode><foia:TimeIncrementProcessedQuantity>0</foia:TimeIncrementProcessedQuantity></foia:TimeIncrement><foia:TimeIncrement><foia:TimeIncrementCode>401+</foia:TimeIncrementCode><foia:TimeIncrementProcessedQuantity>0</foia:TimeIncrementProcessedQuantity></foia:TimeIncrement><foia:TimeIncrementTotalQuantity>2</foia:TimeIncrementTotalQuantity></foia:ComponentResponseTimeIncrements><foia:ResponseTimeIncrementsOrganizationAssociation><foia:ComponentDataReference s:ref="ERT1"/><nc:OrganizationReference s:ref="ORG0"/></foia:ResponseTimeIncrementsOrganizationAssociation></foia:ExpeditedResponseTimeIncrementsSection><foia:PendingPerfectedRequestsSection><foia:PendingPerfectedRequests s:id="PPR0"><foia:SimplePendingRequestStatistics><foia:PendingRequestQuantity>2</foia:PendingRequestQuantity><foia:PendingRequestMedianDaysValue>8</foia:PendingRequestMedianDaysValue><foia:PendingRequestAverageDaysValue>8</foia:PendingRequestAverageDaysValue></foia:SimplePendingRequestStatistics><foia:ComplexPendingRequestStatistics><foia:PendingRequestQuantity>52</foia:PendingRequestQuantity><foia:PendingRequestMedianDaysValue>102</foia:PendingRequestMedianDaysValue><foia:PendingRequestAverageDaysValue>173</foia:PendingRequestAverageDaysValue></foia:ComplexPendingRequestStatistics><foia:ExpeditedPendingRequestStatistics><foia:PendingRequestQuantity>0</foia:PendingRequestQuantity><foia:PendingRequestMedianDaysValue>0</foia:PendingRequestMedianDaysValue><foia:PendingRequestAverageDaysValue>0</foia:PendingRequestAverageDaysValue></foia:ExpeditedPendingRequestStatistics></foia:PendingPerfectedRequests><foia:PendingPerfectedRequestsOrganizationAssociation><foia:ComponentDataReference s:ref="PPR0"/><nc:OrganizationReference s:ref="ORG0"/></foia:PendingPerfectedRequestsOrganizationAssociation></foia:PendingPerfectedRequestsSection><foia:OldestPendingRequestSection><foia:OldestPendingItems s:id="OPR10"><foia:OldItem><foia:OldItemReceiptDate>2006-03-06</foia:OldItemReceiptDate><foia:OldItemPendingDaysQuantity>1401</foia:OldItemPendingDaysQuantity></foia:OldItem><foia:OldItem><foia:OldItemReceiptDate>2010-01-15</foia:OldItemReceiptDate><foia:OldItemPendingDaysQuantity>430</foia:OldItemPendingDaysQuantity></foia:OldItem><foia:OldItem><foia:OldItemReceiptDate>2010-01-19</foia:OldItemReceiptDate><foia:OldItemPendingDaysQuantity>429</foia:OldItemPendingDaysQuantity></foia:OldItem><foia:OldItem><foia:OldItemReceiptDate>2010-02-16</foia:OldItemReceiptDate><foia:OldItemPendingDaysQuantity>410</foia:OldItemPendingDaysQuantity></foia:OldItem><foia:OldItem><foia:OldItemReceiptDate>2010-03-05</foia:OldItemReceiptDate><foia:OldItemPendingDaysQuantity>397</foia:OldItemPendingDaysQuantity></foia:OldItem><foia:OldItem><foia:OldItemReceiptDate>2010-04-20</foia:OldItemReceiptDate><foia:OldItemPendingDaysQuantity>365</foia:OldItemPendingDaysQuantity></foia:OldItem><foia:OldItem><foia:OldItemReceiptDate>2010-04-21</foia:OldItemReceiptDate><foia:OldItemPendingDaysQuantity>364</foia:OldItemPendingDaysQuantity></foia:OldItem><foia:OldItem><foia:OldItemReceiptDate>2010-04-26</foia:OldItemReceiptDate><foia:OldItemPendingDaysQuantity>361</foia:OldItemPendingDaysQuantity></foia:OldItem><foia:OldItem><foia:OldItemReceiptDate>2010-05-21</foia:OldItemReceiptDate><foia:OldItemPendingDaysQuantity>342</foia:OldItemPendingDaysQuantity></foia:OldItem><foia:OldItem><foia:OldItemReceiptDate>2010-07-28</foia:OldItemReceiptDate><foia:OldItemPendingDaysQuantity>296</foia:OldItemPendingDaysQuantity></foia:OldItem></foia:OldestPendingItems><foia:OldestPendingItemsOrganizationAssociation><foia:ComponentDataReference s:ref="OPR10"/><nc:OrganizationReference s:ref="ORG0"/></foia:OldestPendingItemsOrganizationAssociation></foia:OldestPendingRequestSection><foia:ExpeditedProcessingSection><foia:ExpeditedProcessing s:id="EP0"><foia:RequestGrantedQuantity>2</foia:RequestGrantedQuantity><foia:RequestDeniedQuantity>2</foia:RequestDeniedQuantity><foia:AdjudicationMedianDaysValue>1</foia:AdjudicationMedianDaysValue><foia:AdjudicationAverageDaysValue>1</foia:AdjudicationAverageDaysValue><foia:AdjudicationWithinTenDaysQuantity>4</foia:AdjudicationWithinTenDaysQuantity></foia:ExpeditedProcessing><foia:ExpeditedProcessingOrganizationAssociation><foia:ComponentDataReference s:ref="EP0"/><nc:OrganizationReference s:ref="ORG0"/></foia:ExpeditedProcessingOrganizationAssociation></foia:ExpeditedProcessingSection><foia:FeeWaiverSection><foia:FeeWaiver s:id="FW0"><foia:RequestGrantedQuantity>7</foia:RequestGrantedQuantity><foia:RequestDeniedQuantity>0</foia:RequestDeniedQuantity><foia:AdjudicationMedianDaysValue>1</foia:AdjudicationMedianDaysValue><foia:AdjudicationAverageDaysValue>4</foia:AdjudicationAverageDaysValue></foia:FeeWaiver><foia:FeeWaiverOrganizationAssociation><foia:ComponentDataReference s:ref="FW0"/><nc:OrganizationReference s:ref="ORG0"/></foia:FeeWaiverOrganizationAssociation></foia:FeeWaiverSection><foia:PersonnelAndCostSection><foia:PersonnelAndCost s:id="PC1"><foia:FullTimeEmployeeQuantity>1</foia:FullTimeEmployeeQuantity><foia:EquivalentFullTimeEmployeeQuantity>0.5</foia:EquivalentFullTimeEmployeeQuantity><foia:TotalFullTimeStaffQuantity>1.5</foia:TotalFullTimeStaffQuantity><foia:ProcessingCostAmount>80000</foia:ProcessingCostAmount><foia:LitigationCostAmount>0</foia:LitigationCostAmount><foia:TotalCostAmount>80000</foia:TotalCostAmount></foia:PersonnelAndCost><foia:PersonnelAndCostOrganizationAssociation><foia:ComponentDataReference s:ref="PC1"/><nc:OrganizationReference s:ref="ORG0"/></foia:PersonnelAndCostOrganizationAssociation></foia:PersonnelAndCostSection><foia:FeesCollectedSection><foia:FeesCollected s:id="FC1"><foia:FeesCollectedAmount>1188.95</foia:FeesCollectedAmount><foia:FeesCollectedCostPercent>0.0149</foia:FeesCollectedCostPercent></foia:FeesCollected><foia:FeesCollectedOrganizationAssociation><foia:ComponentDataReference s:ref="FC1"/><nc:OrganizationReference s:ref="ORG0"/></foia:FeesCollectedOrganizationAssociation></foia:FeesCollectedSection><foia:BacklogSection><foia:Backlog s:id="BK1"><foia:BackloggedRequestQuantity>15</foia:BackloggedRequestQuantity><foia:BackloggedAppealQuantity>2</foia:BackloggedAppealQuantity></foia:Backlog><foia:BacklogOrganizationAssociation><foia:ComponentDataReference s:ref="BK1"/><nc:OrganizationReference s:ref="ORG0"/></foia:BacklogOrganizationAssociation></foia:BacklogSection><foia:ProcessedConsultationSection><foia:ProcessingStatistics s:id="PCN1"><foia:ProcessingStatisticsPendingAtStartQuantity>0</foia:ProcessingStatisticsPendingAtStartQuantity><foia:ProcessingStatisticsReceivedQuantity>0</foia:ProcessingStatisticsReceivedQuantity><foia:ProcessingStatisticsProcessedQuantity>0</foia:ProcessingStatisticsProcessedQuantity><foia:ProcessingStatisticsPendingAtEndQuantity>0</foia:ProcessingStatisticsPendingAtEndQuantity></foia:ProcessingStatistics><foia:ProcessingStatisticsOrganizationAssociation><foia:ComponentDataReference s:ref="PCN1"/><nc:OrganizationReference s:ref="ORG0"/></foia:ProcessingStatisticsOrganizationAssociation></foia:ProcessedConsultationSection><foia:OldestPendingConsultationSection><foia:OldestPendingItems s:id="OPC10"/><foia:OldestPendingItemsOrganizationAssociation><foia:ComponentDataReference s:ref="OPC10"/><nc:OrganizationReference s:ref="ORG0"/></foia:OldestPendingItemsOrganizationAssociation></foia:OldestPendingConsultationSection><foia:ProcessedRequestComparisonSection><foia:ProcessingComparison s:id="RPC1"><foia:ItemsReceivedLastYearQuantity>203</foia:ItemsReceivedLastYearQuantity><foia:ItemsReceivedCurrentYearQuantity>172</foia:ItemsReceivedCurrentYearQuantity><foia:ItemsProcessedLastYearQuantity>176</foia:ItemsProcessedLastYearQuantity><foia:ItemsProcessedCurrentYearQuantity>171</foia:ItemsProcessedCurrentYearQuantity></foia:ProcessingComparison><foia:ProcessingComparisonOrganizationAssociation><foia:ComponentDataReference s:ref="RPC1"/><nc:OrganizationReference s:ref="ORG0"/></foia:ProcessingComparisonOrganizationAssociation></foia:ProcessedRequestComparisonSection><foia:BackloggedRequestComparisonSection><foia:BacklogComparison s:id="RBC1"><foia:BacklogLastYearQuantity>37</foia:BacklogLastYearQuantity><foia:BacklogCurrentYearQuantity>15</foia:BacklogCurrentYearQuantity></foia:BacklogComparison><foia:BacklogComparisonOrganizationAssociation><foia:ComponentDataReference s:ref="RBC1"/><nc:OrganizationReference s:ref="ORG0"/></foia:BacklogComparisonOrganizationAssociation><foia:FootnoteText>An adjustment had to be made.  Some requests were not entered into the tracking system.</foia:FootnoteText></foia:BackloggedRequestComparisonSection><foia:ProcessedAppealComparisonSection><foia:ProcessingComparison s:id="APC1"><foia:ItemsReceivedLastYearQuantity>5</foia:ItemsReceivedLastYearQuantity><foia:ItemsReceivedCurrentYearQuantity>7</foia:ItemsReceivedCurrentYearQuantity><foia:ItemsProcessedLastYearQuantity>4</foia:ItemsProcessedLastYearQuantity><foia:ItemsProcessedCurrentYearQuantity>7</foia:ItemsProcessedCurrentYearQuantity></foia:ProcessingComparison><foia:ProcessingComparisonOrganizationAssociation><foia:ComponentDataReference s:ref="APC1"/><nc:OrganizationReference s:ref="ORG0"/></foia:ProcessingComparisonOrganizationAssociation></foia:ProcessedAppealComparisonSection><foia:BackloggedAppealComparisonSection><foia:BacklogComparison s:id="ABC1"><foia:BacklogLastYearQuantity>2</foia:BacklogLastYearQuantity><foia:BacklogCurrentYearQuantity>2</foia:BacklogCurrentYearQuantity></foia:BacklogComparison><foia:BacklogComparisonOrganizationAssociation><foia:ComponentDataReference s:ref="ABC1"/><nc:OrganizationReference s:ref="ORG0"/></foia:BacklogComparisonOrganizationAssociation></foia:BackloggedAppealComparisonSection></iepd:FoiaAnnualReport>
