{
    "abbreviation": "FMSHRC", 
    "description": "The Federal Mine Safety and Health Review Commission is an independent agency that administers trials and hears appeals of disputes relating directly to the Mine Safety and Health Act of 1977.", 
    "name": "Federal Mine Safety and Health Review Commission", 
    "keywords": [
        "Administrative practice and procedure", 
        "Civil rights", 
        "Claims", 
        "Equal access to justice", 
        "Equal employment opportunity", 
        "Federal buildings and facilities", 
        "Freedom of information", 
        "Individuals with disabilities", 
        "Lawyers", 
        "Mine safety and health", 
        "Penalties", 
        "Privacy", 
        "Sunshine Act", 
        "Whistleblowing"
    ], 
    "usa_id": "52617", 
    "departments": [
        {
            "reading_rooms": [
                [
                    "E-Reading Room", 
                    "http://www.fmshrc.gov/foia/e-reading-room"
                ]
            ], 
            "service_center": {
                "phone": [
                    "202-434-9935"
                ]
            }, 
            "fax": "202-434-9944", 
            "name": "Federal Mine Safety and Health Review Commission", 
            "request_form": "http://www.fmshrc.gov/foia/foia-request-form", 
            "usa_id": "52617", 
            "request_time_stats": {
                "2014": {
                    "simple_lowest_days": "1", 
                    "complex_lowest_days": "1", 
                    "simple_median_days": "1", 
                    "complex_median_days": "6", 
                    "complex_highest_days": "36", 
                    "simple_highest_days": "25", 
                    "simple_average_days": "3.4", 
                    "complex_average_days": "9.2"
                }, 
                "2008": {
                    "simple_lowest_days": "1", 
                    "complex_lowest_days": "0", 
                    "expedited_processing_average_days": "0", 
                    "expedited_processing_highest_days": "0", 
                    "simple_median_days": "5", 
                    "complex_median_days": "0", 
                    "complex_highest_days": "0", 
                    "simple_highest_days": "24", 
                    "expedited_processing_median_days": "0", 
                    "simple_average_days": "8", 
                    "expedited_processing_lowest_days": "0", 
                    "complex_average_days": "0"
                }, 
                "2009": {
                    "simple_lowest_days": "1", 
                    "complex_lowest_days": "0", 
                    "expedited_processing_average_days": "0", 
                    "expedited_processing_highest_days": "0", 
                    "simple_median_days": "5", 
                    "complex_median_days": "0", 
                    "complex_highest_days": "0", 
                    "simple_highest_days": "20", 
                    "expedited_processing_median_days": "0", 
                    "simple_average_days": "6", 
                    "expedited_processing_lowest_days": "0", 
                    "complex_average_days": "0"
                }, 
                "2011": {
                    "simple_lowest_days": "less than 1", 
                    "complex_lowest_days": "8", 
                    "expedited_processing_average_days": "0", 
                    "expedited_processing_highest_days": "0", 
                    "simple_median_days": "1", 
                    "complex_median_days": "11", 
                    "complex_highest_days": "20", 
                    "simple_highest_days": "36", 
                    "expedited_processing_median_days": "0", 
                    "simple_average_days": "3.3", 
                    "expedited_processing_lowest_days": "0", 
                    "complex_average_days": "12.5"
                }, 
                "2010": {
                    "simple_lowest_days": "1", 
                    "complex_lowest_days": "4", 
                    "expedited_processing_average_days": "0", 
                    "expedited_processing_highest_days": "0", 
                    "simple_median_days": "2", 
                    "complex_median_days": "14.5", 
                    "complex_highest_days": "36", 
                    "simple_highest_days": "22", 
                    "expedited_processing_median_days": "0", 
                    "simple_average_days": "5", 
                    "expedited_processing_lowest_days": "0", 
                    "complex_average_days": "17"
                }, 
                "2013": {
                    "simple_lowest_days": "1", 
                    "complex_lowest_days": "1", 
                    "expedited_processing_average_days": "5.7", 
                    "expedited_processing_highest_days": "9", 
                    "simple_median_days": "1", 
                    "complex_median_days": "6", 
                    "complex_highest_days": "34", 
                    "simple_highest_days": "24", 
                    "expedited_processing_median_days": "7", 
                    "simple_average_days": "3.1", 
                    "expedited_processing_lowest_days": "1", 
                    "complex_average_days": "8.9"
                }, 
                "2012": {
                    "simple_lowest_days": "1", 
                    "complex_lowest_days": "11", 
                    "expedited_processing_average_days": "12.5", 
                    "expedited_processing_highest_days": "17", 
                    "simple_median_days": "1", 
                    "complex_median_days": "18.5", 
                    "complex_highest_days": "31", 
                    "simple_highest_days": "18", 
                    "expedited_processing_median_days": "12.5", 
                    "simple_average_days": "3.6", 
                    "expedited_processing_lowest_days": "8", 
                    "complex_average_days": "16"
                }
            }, 
            "website": "http://www.fmshrc.gov/foia", 
            "phone": "202-434-9935", 
            "foia_officer": {
                "phone": [
                    "202-434-9935"
                ], 
                "name": "Linda H. Ghosal"
            }, 
            "public_liaison": {
                "phone": [
                    "202-434-9935"
                ], 
                "name": "Emogene Johnson"
            }, 
            "address": {
                "address_lines": [
                    "Stacey Demps-Barrett", 
                    "Chief FOIA Officer", 
                    "Suite 520N"
                ], 
                "state": "DC", 
                "street": "1331 Pennsylvania, NW", 
                "zip": "20004-1710", 
                "city": "Washington"
            }, 
            "top_level": false, 
            "emails": [
                "foia@fmshrc.gov"
            ], 
            "description": "The Federal Mine Safety and Health Review Commission is an independent agency that administers trials and hears appeals of disputes relating directly to the Mine Safety and Health Act of 1977."
        }
    ], 
    "request_time_stats": {
        "2014": {
            "simple_lowest_days": "1", 
            "complex_lowest_days": "1", 
            "simple_median_days": "1", 
            "complex_median_days": "6", 
            "complex_highest_days": "36", 
            "simple_highest_days": "25", 
            "simple_average_days": "3.4", 
            "complex_average_days": "9.2"
        }, 
        "2008": {
            "simple_lowest_days": "1", 
            "complex_lowest_days": "0", 
            "expedited_processing_average_days": "0", 
            "expedited_processing_highest_days": "0", 
            "simple_median_days": "5", 
            "complex_median_days": "0", 
            "complex_highest_days": "0", 
            "simple_highest_days": "24", 
            "expedited_processing_median_days": "0", 
            "simple_average_days": "8", 
            "expedited_processing_lowest_days": "0", 
            "complex_average_days": "0"
        }, 
        "2009": {
            "simple_lowest_days": "1", 
            "complex_lowest_days": "0", 
            "expedited_processing_average_days": "0", 
            "expedited_processing_highest_days": "0", 
            "simple_median_days": "5", 
            "complex_median_days": "0", 
            "complex_highest_days": "0", 
            "simple_highest_days": "20", 
            "expedited_processing_median_days": "0", 
            "simple_average_days": "6", 
            "expedited_processing_lowest_days": "0", 
            "complex_average_days": "0"
        }, 
        "2011": {
            "simple_lowest_days": "less than 1", 
            "complex_lowest_days": "8", 
            "expedited_processing_average_days": "0", 
            "expedited_processing_highest_days": "0", 
            "simple_median_days": "1", 
            "complex_median_days": "11", 
            "complex_highest_days": "20", 
            "simple_highest_days": "36", 
            "expedited_processing_median_days": "0", 
            "simple_average_days": "3.3", 
            "expedited_processing_lowest_days": "0", 
            "complex_average_days": "12.5"
        }, 
        "2010": {
            "simple_lowest_days": "1", 
            "complex_lowest_days": "4", 
            "expedited_processing_average_days": "0", 
            "expedited_processing_highest_days": "0", 
            "simple_median_days": "2", 
            "complex_median_days": "14.5", 
            "complex_highest_days": "36", 
            "simple_highest_days": "22", 
            "expedited_processing_median_days": "0", 
            "simple_average_days": "5", 
            "expedited_processing_lowest_days": "0", 
            "complex_average_days": "17"
        }, 
        "2013": {
            "simple_lowest_days": "1", 
            "complex_lowest_days": "1", 
            "expedited_processing_average_days": "5.7", 
            "expedited_processing_highest_days": "9", 
            "simple_median_days": "1", 
            "complex_median_days": "6", 
            "complex_highest_days": "34", 
            "simple_highest_days": "24", 
            "expedited_processing_median_days": "7", 
            "simple_average_days": "3.1", 
            "expedited_processing_lowest_days": "1", 
            "complex_average_days": "8.9"
        }, 
        "2012": {
            "simple_lowest_days": "1", 
            "complex_lowest_days": "11", 
            "expedited_processing_average_days": "12.5", 
            "expedited_processing_highest_days": "17", 
            "simple_median_days": "1", 
            "complex_median_days": "18.5", 
            "complex_highest_days": "31", 
            "simple_highest_days": "18", 
            "expedited_processing_median_days": "12.5", 
            "simple_average_days": "3.6", 
            "expedited_processing_lowest_days": "8", 
            "complex_average_days": "16"
        }
    }
}